rangekeeper/__init__.py
rangekeeper/api.py
rangekeeper/distribution.py
rangekeeper/duration.py
rangekeeper/extrapolation.py
rangekeeper/flux.py
rangekeeper/format.py
rangekeeper/graph.py
rangekeeper/measure.py
rangekeeper/policy.py
rangekeeper/projection.py
rangekeeper/segmentation.py
rangekeeper/space.py
rangekeeper/dynamics/__init__.py
rangekeeper/dynamics/black_swan.py
rangekeeper/dynamics/cyclicality.py
rangekeeper/dynamics/market.py
rangekeeper/dynamics/noise.py
rangekeeper/dynamics/trend.py
rangekeeper/dynamics/volatility.py
rangekeeper/formula/__init__.py
rangekeeper/formula/financial.py
rangekeeper-0.8.62.dist-info/METADATA
rangekeeper-0.8.62.dist-info/WHEEL
rangekeeper-0.8.62.dist-info/top_level.txt
rangekeeper-0.8.62.dist-info/RECORD
