Metadata-Version: 2.4
Name: Rangekeeper
Version: 0.8.62
Summary: A Python library assisting financial modelling in real estate asset & development planning, decision-making, cashflow forecasting, and scenario analysis.
Author-email: Daniel Fink <danfink@mit.edu>
License-Expression: MPL-2.0
Requires-Python: <3.13,>=3.10
Requires-Dist: matplotlib>=3.10
Requires-Dist: pandas>=2.2
Requires-Dist: pint>=0.24
Requires-Dist: pyxirr>=0.9
Requires-Dist: scipy>=1.12
Requires-Dist: networkx>=3.1
Requires-Dist: py-moneyed>=3.0
Requires-Dist: tabulate>=0.9
Requires-Dist: specklepy>=2.21
Requires-Dist: numba>=0.61
Requires-Dist: multiprocess>=0.70.18
Requires-Dist: seaborn>=0.13
Requires-Dist: pyvis>=0.3.2
Requires-Dist: plotly>=6.0
Requires-Dist: aenum>=3.0
Requires-Dist: numpy-financial>=1.0
Requires-Dist: pytest>=8.0
Requires-Dist: black>=25.0
